Workbook

Sheet 使用说明
A1: 公司名称
A2: 四类零件统一报价计算模板—使用说明
A3: 加工件作为基准模式；钣金件、焊接件、型材组装件均采用相同的材料—工序—税金—含税单价—总价结构。
A4: 一、四类计算方式
A5: 类别 | B5: 材料计算 | C5: 主要工序输入 | D5: 未税单价结构 | E5: 对应工作表
A6: 加工件 | B6: 密度×备料长×宽×高×材料单价 | C6: 车/铣/磨/钳/CNC/线切割/表处 | D6: 材料费+各工序输入×原模板费率 | E6: 加工件
A7: 钣金件 | B7: 展开面积×板厚×密度÷利用率×材料单价 | C7: 切割长度、穿孔、折弯、五金、手工、表处 | D7: 材料费+切割费+折弯费+五金+手工+外协 | E7: 钣金件
A8: 焊接件 | B8: BOM净重÷利用率×材料单价 | C8: 备料、组立、焊缝、焊材气体、打磨校形 | D8: 材料费+外购+各工序+焊材辅料+外协 | E8: 焊接件
A9: 型材组装件 | B9: 标准料长取整×kg/m×材料单价 | C9: 切断、钻孔、攻牙、连接件、装配 | D9: 材料费+切割机加+连接件+装配+外协 | E9: 型材组装件
A11: 二、自动增加一行
A12: 步骤 | B12: 操作 | C12: 结果
A13: 1 | B13: 进入对应类别工作表。 | C13: 每类工作表都是Excel表格，不是普通固定区域。
A14: 2 | B14: 在表格最后一行紧邻的下一行输入“产品图号”。 | C14: Excel自动扩展一行，并复制序号、查价、材料费、工序费、税金和总价公式。
A15: 3 | B15: 选择材质并填写橙色/蓝色输入格。 | C15: 材料单价、密度和绿色报价结果自动更新。
A16: 4 | B16: 若由图纸识别程序生成，按零件类别向对应表格追加一行。 | C16: 一张图纸=一行；汇总表统计第7～506行。
A17: 5 | B17: 超过500行时，将统一汇总中的统计上限同步扩大。 | C17: Excel表格仍可继续扩展，但汇总预留范围需要调整。
A18: 三、颜色和审核规则
A19: 颜色 | B19: 含义 | C19: 审核要求
A20: 橙色 | B20: 图纸、订单或人工输入 | C20: 图号、材料、数量、关键工艺输入必须确认
A21: 浅蓝色 | B21: 工序驱动量/工时输入 | C21: AI估算工时属于报价估算，不是最终生产工艺路线
A22: 浅绿色 | B22: 公式自动计算 | C22: 不要手工覆盖；应修改来源参数或输入驱动量
A23: 黄色/亮绿色 | B23: 待复核 / 厂商报价 | C23: 不确定项留待人工确认；厂商价保持可编辑
A24: 四、与加工件源模板的一致性
A25: 项目 | B25: 处理方式
A26: 加工费率 | B26: 沿用源模板：车50、铣45、磨45、钳35、其它30、放电40、快丝25、慢丝70、精雕40、CNC60。
A27: 表面处理 | B27: 沿用源模板：镀铬3、热处理12、阳极12、发黑2，单位均为元/kg。
A28: 税率 | B28: 沿用当前源模板13%，统一放在“基础参数”中，可由财务修改。
A29: 综合加成 | B29: 源模板未单列管理费/利润，因此默认0%；如需要可在基础参数统一调整。

Sheet 统一汇总
A1: 公司名称
A2: 四类零件统一报价汇总
A3: 按各类别工作表第7～506行自动统计。AI预估、税金、含税总价以及有厂商报价行的可比差异会自动进入汇总。
A5: 自动汇总与厂商报价对比
A6: 零件类别 | B6: 对应工作表 | C6: 图纸行数 | D6: 报价数量 | E6: AI预估未税总额 | F6: 税金总额 | G6: 含税总额 | H6: 可比AI预估未税 | I6: 厂商报价未税 | J6: 差价 | K6: 差价占比
A7: 加工件 | B7: 加工件 | C7: =COUNTIF(加工件!$C$7:$C$506,"<>") | D7: =SUM(加工件!$AD$7:$AD$506) | E7: =SUMPRODUCT(加工件!$AF$7:$AF$506,加工件!$AD$7:$AD$506) | F7: =SUMPRODUCT(加工件!$AB$7:$AB$506,加工件!$AD$7:$AD$506) | G7: =SUM(加工件!$AE$7:$AE$506) | H7: =SUMPRODUCT((加工件!$AG$7:$AG$506<>"")*加工件!$AF$7:$AF$506*加工件!$AD$7:$AD$506) | I7: =SUMPRODUCT(加工件!$AG$7:$AG$506*加工件!$AD$7:$AD$506) | J7: =H7-I7 | K7: =IFERROR(J7/H7,"")
A8: 钣金件 | B8: 钣金件 | C8: =COUNTIF(钣金件!$C$7:$C$506,"<>") | D8: =SUM(钣金件!$AD$7:$AD$506) | E8: =SUMPRODUCT(钣金件!$AF$7:$AF$506,钣金件!$AD$7:$AD$506) | F8: =SUMPRODUCT(钣金件!$AB$7:$AB$506,钣金件!$AD$7:$AD$506) | G8: =SUM(钣金件!$AE$7:$AE$506) | H8: =SUMPRODUCT((钣金件!$AG$7:$AG$506<>"")*钣金件!$AF$7:$AF$506*钣金件!$AD$7:$AD$506) | I8: =SUMPRODUCT(钣金件!$AG$7:$AG$506*钣金件!$AD$7:$AD$506) | J8: =H8-I8 | K8: =IFERROR(J8/H8,"")
A9: 焊接件 | B9: 焊接件 | C9: =COUNTIF(焊接件!$C$7:$C$506,"<>") | D9: =SUM(焊接件!$AG$7:$AG$506) | E9: =SUMPRODUCT(焊接件!$AI$7:$AI$506,焊接件!$AG$7:$AG$506) | F9: =SUMPRODUCT(焊接件!$AE$7:$AE$506,焊接件!$AG$7:$AG$506) | G9: =SUM(焊接件!$AH$7:$AH$506) | H9: =SUMPRODUCT((焊接件!$AJ$7:$AJ$506<>"")*焊接件!$AI$7:$AI$506*焊接件!$AG$7:$AG$506) | I9: =SUMPRODUCT(焊接件!$AJ$7:$AJ$506*焊接件!$AG$7:$AG$506) | J9: =H9-I9 | K9: =IFERROR(J9/H9,"")
A10: 型材组装件 | B10: 型材组装件 | C10: =COUNTIF(型材组装件!$C$7:$C$506,"<>") | D10: =SUM(型材组装件!$AH$7:$AH$506) | E10: =SUMPRODUCT(型材组装件!$AJ$7:$AJ$506,型材组装件!$AH$7:$AH$506) | F10: =SUMPRODUCT(型材组装件!$AF$7:$AF$506,型材组装件!$AH$7:$AH$506) | G10: =SUM(型材组装件!$AI$7:$AI$506) | H10: =SUMPRODUCT((型材组装件!$AK$7:$AK$506<>"")*型材组装件!$AJ$7:$AJ$506*型材组装件!$AH$7:$AH$506) | I10: =SUMPRODUCT(型材组装件!$AK$7:$AK$506*型材组装件!$AH$7:$AH$506) | J10: =H10-I10 | K10: =IFERROR(J10/H10,"")
A11: 合计 | B11: 四类 | C11: =SUM(C7:C10) | D11: =SUM(D7:D10) | E11: =SUM(E7:E10) | F11: =SUM(F7:F10) | G11: =SUM(G7:G10) | H11: =SUM(H7:H10) | I11: =SUM(I7:I10) | J11: =H11-I11 | K11: =IFERROR(J11/H11,"")
A12: 说明 | B12: 统计范围预留500行；可比AI预估仅统计已填写厂商报价的行。差价=可比AI预估未税−厂商报价未税，正值表示AI预估较高。

Sheet 加工件
A1: 公司名称
A2: 加工件报价计算（自动增行版）
A3: 完全参照加工件源模板：材料重量=密度×备料长×宽×高；工序输入×对应费率；税率取基础参数。每张图纸一行。
A4: 基本信息 | E4: 材料 | M4: 加工/表面处理输入 | AB4: 报价结果 | AH4: 人工复核 | AK4: 报价对比
A5: 操作：在表格最后一行的下一行输入“产品图号”，Excel会自动增加一行并复制公式、格式和下拉选项。蓝色/橙色为输入，绿色为公式结果。；差价=AI预估未税−厂商报价(未税)，正值表示AI预估较高。
A6: 序号 | B6: 专案代码 | C6: 产品图号 | D6: 材质 | E6: 材料单价 | F6: 密度 | G6: 备料长mm | H6: 备料宽mm | I6: 备料高mm | J6: 单位 | K6: 材料重量kg | L6: 材料费 | M6: 车床h | N6: 铣床h | O6: 磨床h | P6: 钳工h | Q6: 其它h | R6: 放电h | S6: 快丝h | T6: 慢丝h | U6: 夹头/治具费 | V6: 精雕机h | W6: CNC h | X6: 镀铬kg | Y6: 热处理kg | Z6: 阳极kg | AA6: 发黑kg | AB6: 税金 | AC6: 含税单价 | AD6: 数量 | AE6: 含税总价 | AF6: 未税单价 | AG6: 厂商报价(未税) | AH6: 复核状态 | AI6: 备注 | AK6: 差价 | AL6: 占比
A7: =IF($C7="","",ROW()-6) | B7: UC1002001640 | C7: R002 | D7: A6061T6 | E7: =IF($C7="","",IFERROR(VLOOKUP($D7,基础参数!$A$6:$C$22,2,FALSE),"")) | F7: =IF($C7="","",IFERROR(VLOOKUP($D7,基础参数!$A$6:$C$22,3,FALSE),"")) | G7: 125 | H7: 95 | I7: 12 | J7: KG | K7: =IF($C7="","",$F7*$G7*$H7*$I7) | L7: =IF($C7="","",$E7*$K7) | M7: 0 | N7: 0 | O7: 0 | P7: 0 | Q7: 0 | R7: 0 | S7: 0 | T7: 0 | U7: 0 | V7: 0 | W7: 1.5 | X7: 0 | Y7: 0 | Z7: 0.39 | AA7: 0 | AB7: =IF($C7="","",$AF7*基础参数!$N$6) | AC7: =IF($C7="","",$AF7+$AB7) | AD7: 1 | AE7: =IF($C7="","",$AC7*$AD7) | AF7: =IF($C7="","",($L7+$M7*VLOOKUP("LATHE",基础参数!$F$6:$I$30,4,FALSE)+$N7*VLOOKUP("MILL",基础参数!$F$6:$I$30,4,FALSE)+$O7*VLOOKUP("GRIND",基础参数!$F$6:$I$30,4,FALSE)+$P7*VLOOKUP("FITTER",基础参数!$F$6:$I$30,4,FALSE)+$Q7*VLOOKUP("OTHER",基础参数!$F$6:$I$30,4,FALSE)+$R7*VLOOKUP("EDM",基础参数!$F$6:$I$30,4,FALSE)+$S7*VLOOKUP("WIRE_FAST",基础参数!$F$6:$I$30,4,FALSE)+$T7*VLOOKUP("WIRE_SLOW",基础参数!$F$6:$I$30,4,FALSE)+$U7+$V7*VLOOKUP("ENGRAVE",基础参数!$F$6:$I$30,4,FALSE)+$W7*VLOOKUP("CNC",基础参数!$F$6:$I$30,4,FALSE)+$X7*VLOOKUP("CHROME",基础参数!$F$6:$I$30,4,FALSE)+$Y7*VLOOKUP("HEAT",基础参数!$F$6:$I$30,4,FALSE)+$Z7*VLOOKUP("ANODIZE",基础参数!$F$6:$I$30,4,FALSE)+$AA7*VLOOKUP("BLACK",基础参数!$F$6:$I$30,4,FALSE))*(1+基础参数!$N$7)) | AH7: 待复核 | AI7: 示例与源模板R002一致；备料尺寸需人工确认 | AK7: =IF(OR($C7="",AG7=""),"",AF7-AG7) | AL7: =IFERROR(AK7/AF7,"")
A8: =IF($C8="","",ROW()-6) | E8: =IF($C8="","",IFERROR(VLOOKUP($D8,基础参数!$A$6:$C$22,2,FALSE),"")) | F8: =IF($C8="","",IFERROR(VLOOKUP($D8,基础参数!$A$6:$C$22,3,FALSE),"")) | K8: =IF($C8="","",$F8*$G8*$H8*$I8) | L8: =IF($C8="","",$E8*$K8) | AB8: =IF($C8="","",$AF8*基础参数!$N$6) | AC8: =IF($C8="","",$AF8+$AB8) | AE8: =IF($C8="","",$AC8*$AD8) | AF8: =IF($C8="","",($L8+$M8*VLOOKUP("LATHE",基础参数!$F$6:$I$30,4,FALSE)+$N8*VLOOKUP("MILL",基础参数!$F$6:$I$30,4,FALSE)+$O8*VLOOKUP("GRIND",基础参数!$F$6:$I$30,4,FALSE)+$P8*VLOOKUP("FITTER",基础参数!$F$6:$I$30,4,FALSE)+$Q8*VLOOKUP("OTHER",基础参数!$F$6:$I$30,4,FALSE)+$R8*VLOOKUP("EDM",基础参数!$F$6:$I$30,4,FALSE)+$S8*VLOOKUP("WIRE_FAST",基础参数!$F$6:$I$30,4,FALSE)+$T8*VLOOKUP("WIRE_SLOW",基础参数!$F$6:$I$30,4,FALSE)+$U8+$V8*VLOOKUP("ENGRAVE",基础参数!$F$6:$I$30,4,FALSE)+$W8*VLOOKUP("CNC",基础参数!$F$6:$I$30,4,FALSE)+$X8*VLOOKUP("CHROME",基础参数!$F$6:$I$30,4,FALSE)+$Y8*VLOOKUP("HEAT",基础参数!$F$6:$I$30,4,FALSE)+$Z8*VLOOKUP("ANODIZE",基础参数!$F$6:$I$30,4,FALSE)+$AA8*VLOOKUP("BLACK",基础参数!$F$6:$I$30,4,FALSE))*(1+基础参数!$N$7)) | AK8: =IF(OR($C8="",AG8=""),"",AF8-AG8) | AL8: =IFERROR(AK8/AF8,"")
A9: =IF($C9="","",ROW()-6) | E9: =IF($C9="","",IFERROR(VLOOKUP($D9,基础参数!$A$6:$C$22,2,FALSE),"")) | F9: =IF($C9="","",IFERROR(VLOOKUP($D9,基础参数!$A$6:$C$22,3,FALSE),"")) | K9: =IF($C9="","",$F9*$G9*$H9*$I9) | L9: =IF($C9="","",$E9*$K9) | AB9: =IF($C9="","",$AF9*基础参数!$N$6) | AC9: =IF($C9="","",$AF9+$AB9) | AE9: =IF($C9="","",$AC9*$AD9) | AF9: =IF($C9="","",($L9+$M9*VLOOKUP("LATHE",基础参数!$F$6:$I$30,4,FALSE)+$N9*VLOOKUP("MILL",基础参数!$F$6:$I$30,4,FALSE)+$O9*VLOOKUP("GRIND",基础参数!$F$6:$I$30,4,FALSE)+$P9*VLOOKUP("FITTER",基础参数!$F$6:$I$30,4,FALSE)+$Q9*VLOOKUP("OTHER",基础参数!$F$6:$I$30,4,FALSE)+$R9*VLOOKUP("EDM",基础参数!$F$6:$I$30,4,FALSE)+$S9*VLOOKUP("WIRE_FAST",基础参数!$F$6:$I$30,4,FALSE)+$T9*VLOOKUP("WIRE_SLOW",基础参数!$F$6:$I$30,4,FALSE)+$U9+$V9*VLOOKUP("ENGRAVE",基础参数!$F$6:$I$30,4,FALSE)+$W9*VLOOKUP("CNC",基础参数!$F$6:$I$30,4,FALSE)+$X9*VLOOKUP("CHROME",基础参数!$F$6:$I$30,4,FALSE)+$Y9*VLOOKUP("HEAT",基础参数!$F$6:$I$30,4,FALSE)+$Z9*VLOOKUP("ANODIZE",基础参数!$F$6:$I$30,4,FALSE)+$AA9*VLOOKUP("BLACK",基础参数!$F$6:$I$30,4,FALSE))*(1+基础参数!$N$7)) | AK9: =IF(OR($C9="",AG9=""),"",AF9-AG9) | AL9: =IFERROR(AK9/AF9,"")
A10: =IF($C10="","",ROW()-6) | E10: =IF($C10="","",IFERROR(VLOOKUP($D10,基础参数!$A$6:$C$22,2,FALSE),"")) | F10: =IF($C10="","",IFERROR(VLOOKUP($D10,基础参数!$A$6:$C$22,3,FALSE),"")) | K10: =IF($C10="","",$F10*$G10*$H10*$I10) | L10: =IF($C10="","",$E10*$K10) | AB10: =IF($C10="","",$AF10*基础参数!$N$6) | AC10: =IF($C10="","",$AF10+$AB10) | AE10: =IF($C10="","",$AC10*$AD10) | AF10: =IF($C10="","",($L10+$M10*VLOOKUP("LATHE",基础参数!$F$6:$I$30,4,FALSE)+$N10*VLOOKUP("MILL",基础参数!$F$6:$I$30,4,FALSE)+$O10*VLOOKUP("GRIND",基础参数!$F$6:$I$30,4,FALSE)+$P10*VLOOKUP("FITTER",基础参数!$F$6:$I$30,4,FALSE)+$Q10*VLOOKUP("OTHER",基础参数!$F$6:$I$30,4,FALSE)+$R10*VLOOKUP("EDM",基础参数!$F$6:$I$30,4,FALSE)+$S10*VLOOKUP("WIRE_FAST",基础参数!$F$6:$I$30,4,FALSE)+$T10*VLOOKUP("WIRE_SLOW",基础参数!$F$6:$I$30,4,FALSE)+$U10+$V10*VLOOKUP("ENGRAVE",基础参数!$F$6:$I$30,4,FALSE)+$W10*VLOOKUP("CNC",基础参数!$F$6:$I$30,4,FALSE)+$X10*VLOOKUP("CHROME",基础参数!$F$6:$I$30,4,FALSE)+$Y10*VLOOKUP("HEAT",基础参数!$F$6:$I$30,4,FALSE)+$Z10*VLOOKUP("ANODIZE",基础参数!$F$6:$I$30,4,FALSE)+$AA10*VLOOKUP("BLACK",基础参数!$F$6:$I$30,4,FALSE))*(1+基础参数!$N$7)) | AK10: =IF(OR($C10="",AG10=""),"",AF10-AG10) | AL10: =IFERROR(AK10/AF10,"")
A11: =IF($C11="","",ROW()-6) | E11: =IF($C11="","",IFERROR(VLOOKUP($D11,基础参数!$A$6:$C$22,2,FALSE),"")) | F11: =IF($C11="","",IFERROR(VLOOKUP($D11,基础参数!$A$6:$C$22,3,FALSE),"")) | K11: =IF($C11="","",$F11*$G11*$H11*$I11) | L11: =IF($C11="","",$E11*$K11) | AB11: =IF($C11="","",$AF11*基础参数!$N$6) | AC11: =IF($C11="","",$AF11+$AB11) | AE11: =IF($C11="","",$AC11*$AD11) | AF11: =IF($C11="","",($L11+$M11*VLOOKUP("LATHE",基础参数!$F$6:$I$30,4,FALSE)+$N11*VLOOKUP("MILL",基础参数!$F$6:$I$30,4,FALSE)+$O11*VLOOKUP("GRIND",基础参数!$F$6:$I$30,4,FALSE)+$P11*VLOOKUP("FITTER",基础参数!$F$6:$I$30,4,FALSE)+$Q11*VLOOKUP("OTHER",基础参数!$F$6:$I$30,4,FALSE)+$R11*VLOOKUP("EDM",基础参数!$F$6:$I$30,4,FALSE)+$S11*VLOOKUP("WIRE_FAST",基础参数!$F$6:$I$30,4,FALSE)+$T11*VLOOKUP("WIRE_SLOW",基础参数!$F$6:$I$30,4,FALSE)+$U11+$V11*VLOOKUP("ENGRAVE",基础参数!$F$6:$I$30,4,FALSE)+$W11*VLOOKUP("CNC",基础参数!$F$6:$I$30,4,FALSE)+$X11*VLOOKUP("CHROME",基础参数!$F$6:$I$30,4,FALSE)+$Y11*VLOOKUP("HEAT",基础参数!$F$6:$I$30,4,FALSE)+$Z11*VLOOKUP("ANODIZE",基础参数!$F$6:$I$30,4,FALSE)+$AA11*VLOOKUP("BLACK",基础参数!$F$6:$I$30,4,FALSE))*(1+基础参数!$N$7)) | AK11: =IF(OR($C11="",AG11=""),"",AF11-AG11) | AL11: =IFERROR(AK11/AF11,"")
A12: =IF($C12="","",ROW()-6) | E12: =IF($C12="","",IFERROR(VLOOKUP($D12,基础参数!$A$6:$C$22,2,FALSE),"")) | F12: =IF($C12="","",IFERROR(VLOOKUP($D12,基础参数!$A$6:$C$22,3,FALSE),"")) | K12: =IF($C12="","",$F12*$G12*$H12*$I12) | L12: =IF($C12="","",$E12*$K12) | AB12: =IF($C12="","",$AF12*基础参数!$N$6) | AC12: =IF($C12="","",$AF12+$AB12) | AE12: =IF($C12="","",$AC12*$AD12) | AF12: =IF($C12="","",($L12+$M12*VLOOKUP("LATHE",基础参数!$F$6:$I$30,4,FALSE)+$N12*VLOOKUP("MILL",基础参数!$F$6:$I$30,4,FALSE)+$O12*VLOOKUP("GRIND",基础参数!$F$6:$I$30,4,FALSE)+$P12*VLOOKUP("FITTER",基础参数!$F$6:$I$30,4,FALSE)+$Q12*VLOOKUP("OTHER",基础参数!$F$6:$I$30,4,FALSE)+$R12*VLOOKUP("EDM",基础参数!$F$6:$I$30,4,FALSE)+$S12*VLOOKUP("WIRE_FAST",基础参数!$F$6:$I$30,4,FALSE)+$T12*VLOOKUP("WIRE_SLOW",基础参数!$F$6:$I$30,4,FALSE)+$U12+$V12*VLOOKUP("ENGRAVE",基础参数!$F$6:$I$30,4,FALSE)+$W12*VLOOKUP("CNC",基础参数!$F$6:$I$30,4,FALSE)+$X12*VLOOKUP("CHROME",基础参数!$F$6:$I$30,4,FALSE)+$Y12*VLOOKUP("HEAT",基础参数!$F$6:$I$30,4,FALSE)+$Z12*VLOOKUP("ANODIZE",基础参数!$F$6:$I$30,4,FALSE)+$AA12*VLOOKUP("BLACK",基础参数!$F$6:$I$30,4,FALSE))*(1+基础参数!$N$7)) | AK12: =IF(OR($C12="",AG12=""),"",AF12-AG12) | AL12: =IFERROR(AK12/AF12,"")

Sheet 钣金件
A1: 公司名称
A2: 钣金件报价计算（自动增行版）
A3: 与加工件相同的报价表达：材料费+工序费+外购/外协费=未税单价，再计算税金、含税单价和总价。每张图纸一行。
A4: 基本信息 | E4: 材料 | M4: 切割/折弯/辅料输入 | AB4: 报价结果 | AH4: 人工复核 | AK4: 报价对比
A5: 材料用量=展开面积×板厚×密度÷材料利用率；切割费同时考虑切割长度、穿孔和批次准备；折弯费同时考虑折弯数和批次换模。；差价=AI预估未税−厂商报价(未税)，正值表示AI预估较高。
A6: 序号 | B6: 专案代码 | C6: 产品图号 | D6: 材质 | E6: 材料单价 | F6: 密度 | G6: 展开面积m² | H6: 板厚mm | I6: 材料利用率 | J6: 单位 | K6: 材料用量kg | L6: 材料费 | M6: 切割长度m | N6: 穿孔数 | O6: 切割速度m/min | P6: 穿孔秒/次 | Q6: 切割准备h/批 | R6: 切割费 | S6: 折弯数 | T6: 单刀分钟 | U6: 折弯准备h/批 | V6: 折弯费 | W6: 五金/件 | X6: 手工分钟/件 | Y6: 手工费 | Z6: 表处费/件 | AA6: 其它费/件 | AB6: 税金 | AC6: 含税单价 | AD6: 数量 | AE6: 含税总价 | AF6: 未税单价 | AG6: 厂商报价(未税) | AH6: 复核状态 | AI6: 备注 | AK6: 差价 | AL6: 占比
A7: =IF($C7="","",ROW()-6) | B7: SM | C7: SM-EX-001 | D7: SUS304 | E7: =IF($C7="","",IFERROR(VLOOKUP($D7,基础参数!$A$6:$C$22,2,FALSE),"")) | F7: =IF($C7="","",IFERROR(VLOOKUP($D7,基础参数!$A$6:$C$22,3,FALSE),"")) | G7: 0.06 | H7: 1.5 | I7: 0.78 | J7: 件 | K7: =IF($C7="","",IF($I7=0,"",$G7*1000000*$H7*$F7/$I7)) | L7: =IF($C7="","",$K7*$E7) | M7: 1.8 | N7: 14 | O7: 3 | P7: 1.5 | Q7: 0.25 | R7: =IF($C7="","",IF($AD7=0,"",($Q7+$AD7*(($M7/$O7)+($N7*$P7/60))/60)*VLOOKUP("SM_LASER",基础参数!$F$6:$I$30,4,FALSE)/$AD7)) | S7: 4 | T7: 0.35 | U7: 0.25 | V7: =IF($C7="","",IF($AD7=0,"",($U7+$AD7*$S7*$T7/60)*VLOOKUP("SM_BEND",基础参数!$F$6:$I$30,4,FALSE)/$AD7)) | W7: 2 | X7: 2.3 | Y7: =IF($C7="","",$X7/60*VLOOKUP("SM_MANUAL",基础参数!$F$6:$I$30,4,FALSE)) | Z7: 0 | AA7: 1.5 | AB7: =IF($C7="","",$AF7*基础参数!$N$6) | AC7: =IF($C7="","",$AF7+$AB7) | AD7: 20 | AE7: =IF($C7="","",$AC7*$AD7) | AF7: =IF($C7="","",SUM($L7,$R7,$V7,$W7,$Y7:$AA7)*(1+基础参数!$N$7)) | AH7: 待复核 | AI7: 示例：SUS304薄板激光+折弯；利用率和工时需校准 | AK7: =IF(OR($C7="",AG7=""),"",AF7-AG7) | AL7: =IFERROR(AK7/AF7,"")
A8: =IF($C8="","",ROW()-6) | E8: =IF($C8="","",IFERROR(VLOOKUP($D8,基础参数!$A$6:$C$22,2,FALSE),"")) | F8: =IF($C8="","",IFERROR(VLOOKUP($D8,基础参数!$A$6:$C$22,3,FALSE),"")) | K8: =IF($C8="","",IF($I8=0,"",$G8*1000000*$H8*$F8/$I8)) | L8: =IF($C8="","",$K8*$E8) | R8: =IF($C8="","",IF($AD8=0,"",($Q8+$AD8*(($M8/$O8)+($N8*$P8/60))/60)*VLOOKUP("SM_LASER",基础参数!$F$6:$I$30,4,FALSE)/$AD8)) | V8: =IF($C8="","",IF($AD8=0,"",($U8+$AD8*$S8*$T8/60)*VLOOKUP("SM_BEND",基础参数!$F$6:$I$30,4,FALSE)/$AD8)) | Y8: =IF($C8="","",$X8/60*VLOOKUP("SM_MANUAL",基础参数!$F$6:$I$30,4,FALSE)) | AB8: =IF($C8="","",$AF8*基础参数!$N$6) | AC8: =IF($C8="","",$AF8+$AB8) | AE8: =IF($C8="","",$AC8*$AD8) | AF8: =IF($C8="","",SUM($L8,$R8,$V8,$W8,$Y8:$AA8)*(1+基础参数!$N$7)) | AK8: =IF(OR($C8="",AG8=""),"",AF8-AG8) | AL8: =IFERROR(AK8/AF8,"")
A9: =IF($C9="","",ROW()-6) | E9: =IF($C9="","",IFERROR(VLOOKUP($D9,基础参数!$A$6:$C$22,2,FALSE),"")) | F9: =IF($C9="","",IFERROR(VLOOKUP($D9,基础参数!$A$6:$C$22,3,FALSE),"")) | K9: =IF($C9="","",IF($I9=0,"",$G9*1000000*$H9*$F9/$I9)) | L9: =IF($C9="","",$K9*$E9) | R9: =IF($C9="","",IF($AD9=0,"",($Q9+$AD9*(($M9/$O9)+($N9*$P9/60))/60)*VLOOKUP("SM_LASER",基础参数!$F$6:$I$30,4,FALSE)/$AD9)) | V9: =IF($C9="","",IF($AD9=0,"",($U9+$AD9*$S9*$T9/60)*VLOOKUP("SM_BEND",基础参数!$F$6:$I$30,4,FALSE)/$AD9)) | Y9: =IF($C9="","",$X9/60*VLOOKUP("SM_MANUAL",基础参数!$F$6:$I$30,4,FALSE)) | AB9: =IF($C9="","",$AF9*基础参数!$N$6) | AC9: =IF($C9="","",$AF9+$AB9) | AE9: =IF($C9="","",$AC9*$AD9) | AF9: =IF($C9="","",SUM($L9,$R9,$V9,$W9,$Y9:$AA9)*(1+基础参数!$N$7)) | AK9: =IF(OR($C9="",AG9=""),"",AF9-AG9) | AL9: =IFERROR(AK9/AF9,"")
A10: =IF($C10="","",ROW()-6) | E10: =IF($C10="","",IFERROR(VLOOKUP($D10,基础参数!$A$6:$C$22,2,FALSE),"")) | F10: =IF($C10="","",IFERROR(VLOOKUP($D10,基础参数!$A$6:$C$22,3,FALSE),"")) | K10: =IF($C10="","",IF($I10=0,"",$G10*1000000*$H10*$F10/$I10)) | L10: =IF($C10="","",$K10*$E10) | R10: =IF($C10="","",IF($AD10=0,"",($Q10+$AD10*(($M10/$O10)+($N10*$P10/60))/60)*VLOOKUP("SM_LASER",基础参数!$F$6:$I$30,4,FALSE)/$AD10)) | V10: =IF($C10="","",IF($AD10=0,"",($U10+$AD10*$S10*$T10/60)*VLOOKUP("SM_BEND",基础参数!$F$6:$I$30,4,FALSE)/$AD10)) | Y10: =IF($C10="","",$X10/60*VLOOKUP("SM_MANUAL",基础参数!$F$6:$I$30,4,FALSE)) | AB10: =IF($C10="","",$AF10*基础参数!$N$6) | AC10: =IF($C10="","",$AF10+$AB10) | AE10: =IF($C10="","",$AC10*$AD10) | AF10: =IF($C10="","",SUM($L10,$R10,$V10,$W10,$Y10:$AA10)*(1+基础参数!$N$7)) | AK10: =IF(OR($C10="",AG10=""),"",AF10-AG10) | AL10: =IFERROR(AK10/AF10,"")
A11: =IF($C11="","",ROW()-6) | E11: =IF($C11="","",IFERROR(VLOOKUP($D11,基础参数!$A$6:$C$22,2,FALSE),"")) | F11: =IF($C11="","",IFERROR(VLOOKUP($D11,基础参数!$A$6:$C$22,3,FALSE),"")) | K11: =IF($C11="","",IF($I11=0,"",$G11*1000000*$H11*$F11/$I11)) | L11: =IF($C11="","",$K11*$E11) | R11: =IF($C11="","",IF($AD11=0,"",($Q11+$AD11*(($M11/$O11)+($N11*$P11/60))/60)*VLOOKUP("SM_LASER",基础参数!$F$6:$I$30,4,FALSE)/$AD11)) | V11: =IF($C11="","",IF($AD11=0,"",($U11+$AD11*$S11*$T11/60)*VLOOKUP("SM_BEND",基础参数!$F$6:$I$30,4,FALSE)/$AD11)) | Y11: =IF($C11="","",$X11/60*VLOOKUP("SM_MANUAL",基础参数!$F$6:$I$30,4,FALSE)) | AB11: =IF($C11="","",$AF11*基础参数!$N$6) | AC11: =IF($C11="","",$AF11+$AB11) | AE11: =IF($C11="","",$AC11*$AD11) | AF11: =IF($C11="","",SUM($L11,$R11,$V11,$W11,$Y11:$AA11)*(1+基础参数!$N$7)) | AK11: =IF(OR($C11="",AG11=""),"",AF11-AG11) | AL11: =IFERROR(AK11/AF11,"")
A12: =IF($C12="","",ROW()-6) | E12: =IF($C12="","",IFERROR(VLOOKUP($D12,基础参数!$A$6:$C$22,2,FALSE),"")) | F12: =IF($C12="","",IFERROR(VLOOKUP($D12,基础参数!$A$6:$C$22,3,FALSE),"")) | K12: =IF($C12="","",IF($I12=0,"",$G12*1000000*$H12*$F12/$I12)) | L12: =IF($C12="","",$K12*$E12) | R12: =IF($C12="","",IF($AD12=0,"",($Q12+$AD12*(($M12/$O12)+($N12*$P12/60))/60)*VLOOKUP("SM_LASER",基础参数!$F$6:$I$30,4,FALSE)/$AD12)) | V12: =IF($C12="","",IF($AD12=0,"",($U12+$AD12*$S12*$T12/60)*VLOOKUP("SM_BEND",基础参数!$F$6:$I$30,4,FALSE)/$AD12)) | Y12: =IF($C12="","",$X12/60*VLOOKUP("SM_MANUAL",基础参数!$F$6:$I$30,4,FALSE)) | AB12: =IF($C12="","",$AF12*基础参数!$N$6) | AC12: =IF($C12="","",$AF12+$AB12) | AE12: =IF($C12="","",$AC12*$AD12) | AF12: =IF($C12="","",SUM($L12,$R12,$V12,$W12,$Y12:$AA12)*(1+基础参数!$N$7)) | AK12: =IF(OR($C12="",AG12=""),"",AF12-AG12) | AL12: =IFERROR(AK12/AF12,"")

Sheet 焊接件
A1: 公司名称
A2: 焊接件报价计算（自动增行版）
A3: 材料按BOM净重和利用率计价；焊接按焊缝长度、截面积、焊速、电弧作业率计工时和焊材。报价结果位置与加工件一致。
A4: 基本信息 | E4: 材料/备料/组立 | P4: 焊接/后处理输入 | AE4: 报价结果 | AK4: 人工复核 | AN4: 报价对比
A5: 焊工实际工时=电弧时间÷电弧作业率；焊材费=焊缝体积×密度÷熔敷效率×焊材单价。坡口焊须按实际截面积调整系数。；差价=AI预估未税−厂商报价(未税)，正值表示AI预估较高。
A6: 序号 | B6: 专案代码 | C6: 产品图号 | D6: 材质 | E6: 材料单价 | F6: 密度 | G6: BOM净重kg/套 | H6: 材料利用率 | I6: 材料用量kg/套 | J6: 材料费 | K6: 外购件/套 | L6: 备料h/批 | M6: 备料费/套 | N6: 组立h/套 | O6: 组立费/套 | P6: 焊缝长度m/套 | Q6: 焊脚/特征mm | R6: 截面积系数 | S6: 焊速m/min | T6: 电弧作业率 | U6: 焊工实际h/套 | V6: 焊接费/套 | W6: 焊材单价 | X6: 熔敷效率 | Y6: 气体费率元/h | Z6: 焊材+气体费/套 | AA6: 打磨校形h/套 | AB6: 后处理费/套 | AC6: 表处/外协/套 | AD6: 检验包装/套 | AE6: 税金 | AF6: 含税单价 | AG6: 数量 | AH6: 含税总价 | AI6: 未税单价 | AJ6: 厂商报价(未税) | AK6: 复核状态 | AL6: 备注 | AN6: 差价 | AO6: 占比
A7: =IF($C7="","",ROW()-6) | B7: WELD | C7: WELD-EX-001 | D7: Q235 | E7: =IF($C7="","",IFERROR(VLOOKUP($D7,基础参数!$A$6:$C$22,2,FALSE),"")) | F7: =IF($C7="","",IFERROR(VLOOKUP($D7,基础参数!$A$6:$C$22,3,FALSE),"")) | G7: 18.5 | H7: 0.95 | I7: =IF($C7="","",IF($H7=0,"",$G7/$H7)) | J7: =IF($C7="","",$I7*$E7) | K7: 20 | L7: 1.2 | M7: =IF($C7="","",IF($AG7=0,"",$L7*VLOOKUP("WELD_PREP",基础参数!$F$6:$I$30,4,FALSE)/$AG7)) | N7: 0.6 | O7: =IF($C7="","",$N7*VLOOKUP("WELD_FIT",基础参数!$F$6:$I$30,4,FALSE)) | P7: 4 | Q7: 5 | R7: 0.5 | S7: 0.25 | T7: 0.35 | U7: =IF($C7="","",IF($S7*$T7=0,"",$P7/$S7/60/$T7)) | V7: =IF($C7="","",$U7*VLOOKUP("WELD",基础参数!$F$6:$I$30,4,FALSE)) | W7: 14 | X7: 0.85 | Y7: 8 | Z7: =IF($C7="","",IF($X7=0,"",($R7*$Q7^2*$P7*1000*$F7/$X7)*$W7+$U7*$Y7)) | AA7: 0.4 | AB7: =IF($C7="","",$AA7*VLOOKUP("WELD_POST",基础参数!$F$6:$I$30,4,FALSE)) | AC7: 42.84 | AD7: 8 | AE7: =IF($C7="","",$AI7*基础参数!$N$6) | AF7: =IF($C7="","",$AI7+$AE7) | AG7: 5 | AH7: =IF($C7="","",$AF7*$AG7) | AI7: =IF($C7="","",SUM($J7,$K7,$M7,$O7,$V7,$Z7,$AB7:$AD7)*(1+基础参数!$N$7)) | AK7: 待复核 | AL7: 示例：Q235框架；焊缝类型、夹具和表面要求需确认 | AN7: =IF(OR($C7="",AJ7=""),"",AI7-AJ7) | AO7: =IFERROR(AN7/AI7,"")
A8: =IF($C8="","",ROW()-6) | E8: =IF($C8="","",IFERROR(VLOOKUP($D8,基础参数!$A$6:$C$22,2,FALSE),"")) | F8: =IF($C8="","",IFERROR(VLOOKUP($D8,基础参数!$A$6:$C$22,3,FALSE),"")) | I8: =IF($C8="","",IF($H8=0,"",$G8/$H8)) | J8: =IF($C8="","",$I8*$E8) | M8: =IF($C8="","",IF($AG8=0,"",$L8*VLOOKUP("WELD_PREP",基础参数!$F$6:$I$30,4,FALSE)/$AG8)) | O8: =IF($C8="","",$N8*VLOOKUP("WELD_FIT",基础参数!$F$6:$I$30,4,FALSE)) | U8: =IF($C8="","",IF($S8*$T8=0,"",$P8/$S8/60/$T8)) | V8: =IF($C8="","",$U8*VLOOKUP("WELD",基础参数!$F$6:$I$30,4,FALSE)) | Z8: =IF($C8="","",IF($X8=0,"",($R8*$Q8^2*$P8*1000*$F8/$X8)*$W8+$U8*$Y8)) | AB8: =IF($C8="","",$AA8*VLOOKUP("WELD_POST",基础参数!$F$6:$I$30,4,FALSE)) | AE8: =IF($C8="","",$AI8*基础参数!$N$6) | AF8: =IF($C8="","",$AI8+$AE8) | AH8: =IF($C8="","",$AF8*$AG8) | AI8: =IF($C8="","",SUM($J8,$K8,$M8,$O8,$V8,$Z8,$AB8:$AD8)*(1+基础参数!$N$7)) | AN8: =IF(OR($C8="",AJ8=""),"",AI8-AJ8) | AO8: =IFERROR(AN8/AI8,"")
A9: =IF($C9="","",ROW()-6) | E9: =IF($C9="","",IFERROR(VLOOKUP($D9,基础参数!$A$6:$C$22,2,FALSE),"")) | F9: =IF($C9="","",IFERROR(VLOOKUP($D9,基础参数!$A$6:$C$22,3,FALSE),"")) | I9: =IF($C9="","",IF($H9=0,"",$G9/$H9)) | J9: =IF($C9="","",$I9*$E9) | M9: =IF($C9="","",IF($AG9=0,"",$L9*VLOOKUP("WELD_PREP",基础参数!$F$6:$I$30,4,FALSE)/$AG9)) | O9: =IF($C9="","",$N9*VLOOKUP("WELD_FIT",基础参数!$F$6:$I$30,4,FALSE)) | U9: =IF($C9="","",IF($S9*$T9=0,"",$P9/$S9/60/$T9)) | V9: =IF($C9="","",$U9*VLOOKUP("WELD",基础参数!$F$6:$I$30,4,FALSE)) | Z9: =IF($C9="","",IF($X9=0,"",($R9*$Q9^2*$P9*1000*$F9/$X9)*$W9+$U9*$Y9)) | AB9: =IF($C9="","",$AA9*VLOOKUP("WELD_POST",基础参数!$F$6:$I$30,4,FALSE)) | AE9: =IF($C9="","",$AI9*基础参数!$N$6) | AF9: =IF($C9="","",$AI9+$AE9) | AH9: =IF($C9="","",$AF9*$AG9) | AI9: =IF($C9="","",SUM($J9,$K9,$M9,$O9,$V9,$Z9,$AB9:$AD9)*(1+基础参数!$N$7)) | AN9: =IF(OR($C9="",AJ9=""),"",AI9-AJ9) | AO9: =IFERROR(AN9/AI9,"")
A10: =IF($C10="","",ROW()-6) | E10: =IF($C10="","",IFERROR(VLOOKUP($D10,基础参数!$A$6:$C$22,2,FALSE),"")) | F10: =IF($C10="","",IFERROR(VLOOKUP($D10,基础参数!$A$6:$C$22,3,FALSE),"")) | I10: =IF($C10="","",IF($H10=0,"",$G10/$H10)) | J10: =IF($C10="","",$I10*$E10) | M10: =IF($C10="","",IF($AG10=0,"",$L10*VLOOKUP("WELD_PREP",基础参数!$F$6:$I$30,4,FALSE)/$AG10)) | O10: =IF($C10="","",$N10*VLOOKUP("WELD_FIT",基础参数!$F$6:$I$30,4,FALSE)) | U10: =IF($C10="","",IF($S10*$T10=0,"",$P10/$S10/60/$T10)) | V10: =IF($C10="","",$U10*VLOOKUP("WELD",基础参数!$F$6:$I$30,4,FALSE)) | Z10: =IF($C10="","",IF($X10=0,"",($R10*$Q10^2*$P10*1000*$F10/$X10)*$W10+$U10*$Y10)) | AB10: =IF($C10="","",$AA10*VLOOKUP("WELD_POST",基础参数!$F$6:$I$30,4,FALSE)) | AE10: =IF($C10="","",$AI10*基础参数!$N$6) | AF10: =IF($C10="","",$AI10+$AE10) | AH10: =IF($C10="","",$AF10*$AG10) | AI10: =IF($C10="","",SUM($J10,$K10,$M10,$O10,$V10,$Z10,$AB10:$AD10)*(1+基础参数!$N$7)) | AN10: =IF(OR($C10="",AJ10=""),"",AI10-AJ10) | AO10: =IFERROR(AN10/AI10,"")
A11: =IF($C11="","",ROW()-6) | E11: =IF($C11="","",IFERROR(VLOOKUP($D11,基础参数!$A$6:$C$22,2,FALSE),"")) | F11: =IF($C11="","",IFERROR(VLOOKUP($D11,基础参数!$A$6:$C$22,3,FALSE),"")) | I11: =IF($C11="","",IF($H11=0,"",$G11/$H11)) | J11: =IF($C11="","",$I11*$E11) | M11: =IF($C11="","",IF($AG11=0,"",$L11*VLOOKUP("WELD_PREP",基础参数!$F$6:$I$30,4,FALSE)/$AG11)) | O11: =IF($C11="","",$N11*VLOOKUP("WELD_FIT",基础参数!$F$6:$I$30,4,FALSE)) | U11: =IF($C11="","",IF($S11*$T11=0,"",$P11/$S11/60/$T11)) | V11: =IF($C11="","",$U11*VLOOKUP("WELD",基础参数!$F$6:$I$30,4,FALSE)) | Z11: =IF($C11="","",IF($X11=0,"",($R11*$Q11^2*$P11*1000*$F11/$X11)*$W11+$U11*$Y11)) | AB11: =IF($C11="","",$AA11*VLOOKUP("WELD_POST",基础参数!$F$6:$I$30,4,FALSE)) | AE11: =IF($C11="","",$AI11*基础参数!$N$6) | AF11: =IF($C11="","",$AI11+$AE11) | AH11: =IF($C11="","",$AF11*$AG11) | AI11: =IF($C11="","",SUM($J11,$K11,$M11,$O11,$V11,$Z11,$AB11:$AD11)*(1+基础参数!$N$7)) | AN11: =IF(OR($C11="",AJ11=""),"",AI11-AJ11) | AO11: =IFERROR(AN11/AI11,"")
A12: =IF($C12="","",ROW()-6) | E12: =IF($C12="","",IFERROR(VLOOKUP($D12,基础参数!$A$6:$C$22,2,FALSE),"")) | F12: =IF($C12="","",IFERROR(VLOOKUP($D12,基础参数!$A$6:$C$22,3,FALSE),"")) | I12: =IF($C12="","",IF($H12=0,"",$G12/$H12)) | J12: =IF($C12="","",$I12*$E12) | M12: =IF($C12="","",IF($AG12=0,"",$L12*VLOOKUP("WELD_PREP",基础参数!$F$6:$I$30,4,FALSE)/$AG12)) | O12: =IF($C12="","",$N12*VLOOKUP("WELD_FIT",基础参数!$F$6:$I$30,4,FALSE)) | U12: =IF($C12="","",IF($S12*$T12=0,"",$P12/$S12/60/$T12)) | V12: =IF($C12="","",$U12*VLOOKUP("WELD",基础参数!$F$6:$I$30,4,FALSE)) | Z12: =IF($C12="","",IF($X12=0,"",($R12*$Q12^2*$P12*1000*$F12/$X12)*$W12+$U12*$Y12)) | AB12: =IF($C12="","",$AA12*VLOOKUP("WELD_POST",基础参数!$F$6:$I$30,4,FALSE)) | AE12: =IF($C12="","",$AI12*基础参数!$N$6) | AF12: =IF($C12="","",$AI12+$AE12) | AH12: =IF($C12="","",$AF12*$AG12) | AI12: =IF($C12="","",SUM($J12,$K12,$M12,$O12,$V12,$Z12,$AB12:$AD12)*(1+基础参数!$N$7)) | AN12: =IF(OR($C12="",AJ12=""),"",AI12-AJ12) | AO12: =IFERROR(AN12/AI12,"")

Sheet 型材组装件
A1: 公司名称
A2: 型材组装件报价计算（自动增行版）
A3: 材料按净长度、kg/m、标准料长和排料利用率取整；加工按切断、钻孔、攻牙、连接件和装配计价。报价结果位置与加工件一致。
A4: 基本信息 | E4: 型材采购 | N4: 切割/机加/装配输入 | AF4: 报价结果 | AL4: 人工复核 | AO4: 报价对比
A5: 采购支数=向上取整[批次净长度÷(标准料长×排料利用率)]；不可回用余料由当前订单承担。超出表格末行时继续输入即可自动增加。；差价=AI预估未税−厂商报价(未税)，正值表示AI预估较高。
A6: 序号 | B6: 专案代码 | C6: 产品图号 | D6: 材质 | E6: 材料单价 | F6: 密度 | G6: 净长度m/套 | H6: 理论重量kg/m | I6: 标准料长m/支 | J6: 排料利用率 | K6: 采购支数/批 | L6: 采购重量kg/套 | M6: 材料费 | N6: 切断数/套 | O6: 单刀分钟 | P6: 锯切准备h/批 | Q6: 锯切费/套 | R6: 钻孔数/套 | S6: 钻孔单孔分钟 | T6: 钻孔费/套 | U6: 攻牙数/套 | V6: 攻牙单孔分钟 | W6: 攻牙费/套 | X6: 连接件/套 | Y6: 紧固件/套 | Z6: 装配分钟/套 | AA6: 装配费/套 | AB6: 补充焊接分钟/套 | AC6: 焊接费/套 | AD6: 表处/外协/套 | AE6: 检验包装/套 | AF6: 税金 | AG6: 含税单价 | AH6: 数量 | AI6: 含税总价 | AJ6: 未税单价 | AK6: 厂商报价(未税) | AL6: 复核状态 | AM6: 备注 | AO6: 差价 | AP6: 占比
A7: =IF($C7="","",ROW()-6) | B7: PROFILE | C7: PROFILE-EX-001 | D7: A6061T6 | E7: =IF($C7="","",IFERROR(VLOOKUP($D7,基础参数!$A$6:$C$22,2,FALSE),"")) | F7: =IF($C7="","",IFERROR(VLOOKUP($D7,基础参数!$A$6:$C$22,3,FALSE),"")) | G7: 5.6 | H7: 1.85 | I7: 6 | J7: 0.88 | K7: =IF($C7="","",IF($I7*$J7=0,"",ROUNDUP($AH7*$G7/($I7*$J7),0))) | L7: =IF($C7="","",IF($AH7=0,"",$K7*$I7*$H7/$AH7)) | M7: =IF($C7="","",$L7*$E7) | N7: 8 | O7: 0.45 | P7: 0.25 | Q7: =IF($C7="","",IF($AH7=0,"",($P7+$AH7*$N7*$O7/60)*VLOOKUP("PROFILE_SAW",基础参数!$F$6:$I$30,4,FALSE)/$AH7)) | R7: 12 | S7: 0.35 | T7: =IF($C7="","",$R7*$S7/60*VLOOKUP("PROFILE_DRILL",基础参数!$F$6:$I$30,4,FALSE)) | U7: 8 | V7: 0.4 | W7: =IF($C7="","",$U7*$V7/60*VLOOKUP("PROFILE_TAP",基础参数!$F$6:$I$30,4,FALSE)) | X7: 26 | Y7: 8 | Z7: 25 | AA7: =IF($C7="","",$Z7/60*VLOOKUP("PROFILE_ASSEMBLY",基础参数!$F$6:$I$30,4,FALSE)) | AB7: 0 | AC7: =IF($C7="","",$AB7/60*VLOOKUP("WELD",基础参数!$F$6:$I$30,4,FALSE)) | AD7: 35 | AE7: 5 | AF7: =IF($C7="","",$AJ7*基础参数!$N$6) | AG7: =IF($C7="","",$AJ7+$AF7) | AH7: 10 | AI7: =IF($C7="","",$AG7*$AH7) | AJ7: =IF($C7="","",SUM($M7,$Q7,$T7,$W7:$Y7,$AA7,$AC7:$AE7)*(1+基础参数!$N$7)) | AL7: 待复核 | AM7: 示例：6061工业铝型材框架；余料回用和装配精度需确认 | AO7: =IF(OR($C7="",AK7=""),"",AJ7-AK7) | AP7: =IFERROR(AO7/AJ7,"")
A8: =IF($C8="","",ROW()-6) | E8: =IF($C8="","",IFERROR(VLOOKUP($D8,基础参数!$A$6:$C$22,2,FALSE),"")) | F8: =IF($C8="","",IFERROR(VLOOKUP($D8,基础参数!$A$6:$C$22,3,FALSE),"")) | K8: =IF($C8="","",IF($I8*$J8=0,"",ROUNDUP($AH8*$G8/($I8*$J8),0))) | L8: =IF($C8="","",IF($AH8=0,"",$K8*$I8*$H8/$AH8)) | M8: =IF($C8="","",$L8*$E8) | Q8: =IF($C8="","",IF($AH8=0,"",($P8+$AH8*$N8*$O8/60)*VLOOKUP("PROFILE_SAW",基础参数!$F$6:$I$30,4,FALSE)/$AH8)) | T8: =IF($C8="","",$R8*$S8/60*VLOOKUP("PROFILE_DRILL",基础参数!$F$6:$I$30,4,FALSE)) | W8: =IF($C8="","",$U8*$V8/60*VLOOKUP("PROFILE_TAP",基础参数!$F$6:$I$30,4,FALSE)) | AA8: =IF($C8="","",$Z8/60*VLOOKUP("PROFILE_ASSEMBLY",基础参数!$F$6:$I$30,4,FALSE)) | AC8: =IF($C8="","",$AB8/60*VLOOKUP("WELD",基础参数!$F$6:$I$30,4,FALSE)) | AF8: =IF($C8="","",$AJ8*基础参数!$N$6) | AG8: =IF($C8="","",$AJ8+$AF8) | AI8: =IF($C8="","",$AG8*$AH8) | AJ8: =IF($C8="","",SUM($M8,$Q8,$T8,$W8:$Y8,$AA8,$AC8:$AE8)*(1+基础参数!$N$7)) | AO8: =IF(OR($C8="",AK8=""),"",AJ8-AK8) | AP8: =IFERROR(AO8/AJ8,"")
A9: =IF($C9="","",ROW()-6) | E9: =IF($C9="","",IFERROR(VLOOKUP($D9,基础参数!$A$6:$C$22,2,FALSE),"")) | F9: =IF($C9="","",IFERROR(VLOOKUP($D9,基础参数!$A$6:$C$22,3,FALSE),"")) | K9: =IF($C9="","",IF($I9*$J9=0,"",ROUNDUP($AH9*$G9/($I9*$J9),0))) | L9: =IF($C9="","",IF($AH9=0,"",$K9*$I9*$H9/$AH9)) | M9: =IF($C9="","",$L9*$E9) | Q9: =IF($C9="","",IF($AH9=0,"",($P9+$AH9*$N9*$O9/60)*VLOOKUP("PROFILE_SAW",基础参数!$F$6:$I$30,4,FALSE)/$AH9)) | T9: =IF($C9="","",$R9*$S9/60*VLOOKUP("PROFILE_DRILL",基础参数!$F$6:$I$30,4,FALSE)) | W9: =IF($C9="","",$U9*$V9/60*VLOOKUP("PROFILE_TAP",基础参数!$F$6:$I$30,4,FALSE)) | AA9: =IF($C9="","",$Z9/60*VLOOKUP("PROFILE_ASSEMBLY",基础参数!$F$6:$I$30,4,FALSE)) | AC9: =IF($C9="","",$AB9/60*VLOOKUP("WELD",基础参数!$F$6:$I$30,4,FALSE)) | AF9: =IF($C9="","",$AJ9*基础参数!$N$6) | AG9: =IF($C9="","",$AJ9+$AF9) | AI9: =IF($C9="","",$AG9*$AH9) | AJ9: =IF($C9="","",SUM($M9,$Q9,$T9,$W9:$Y9,$AA9,$AC9:$AE9)*(1+基础参数!$N$7)) | AO9: =IF(OR($C9="",AK9=""),"",AJ9-AK9) | AP9: =IFERROR(AO9/AJ9,"")
A10: =IF($C10="","",ROW()-6) | E10: =IF($C10="","",IFERROR(VLOOKUP($D10,基础参数!$A$6:$C$22,2,FALSE),"")) | F10: =IF($C10="","",IFERROR(VLOOKUP($D10,基础参数!$A$6:$C$22,3,FALSE),"")) | K10: =IF($C10="","",IF($I10*$J10=0,"",ROUNDUP($AH10*$G10/($I10*$J10),0))) | L10: =IF($C10="","",IF($AH10=0,"",$K10*$I10*$H10/$AH10)) | M10: =IF($C10="","",$L10*$E10) | Q10: =IF($C10="","",IF($AH10=0,"",($P10+$AH10*$N10*$O10/60)*VLOOKUP("PROFILE_SAW",基础参数!$F$6:$I$30,4,FALSE)/$AH10)) | T10: =IF($C10="","",$R10*$S10/60*VLOOKUP("PROFILE_DRILL",基础参数!$F$6:$I$30,4,FALSE)) | W10: =IF($C10="","",$U10*$V10/60*VLOOKUP("PROFILE_TAP",基础参数!$F$6:$I$30,4,FALSE)) | AA10: =IF($C10="","",$Z10/60*VLOOKUP("PROFILE_ASSEMBLY",基础参数!$F$6:$I$30,4,FALSE)) | AC10: =IF($C10="","",$AB10/60*VLOOKUP("WELD",基础参数!$F$6:$I$30,4,FALSE)) | AF10: =IF($C10="","",$AJ10*基础参数!$N$6) | AG10: =IF($C10="","",$AJ10+$AF10) | AI10: =IF($C10="","",$AG10*$AH10) | AJ10: =IF($C10="","",SUM($M10,$Q10,$T10,$W10:$Y10,$AA10,$AC10:$AE10)*(1+基础参数!$N$7)) | AO10: =IF(OR($C10="",AK10=""),"",AJ10-AK10) | AP10: =IFERROR(AO10/AJ10,"")
A11: =IF($C11="","",ROW()-6) | E11: =IF($C11="","",IFERROR(VLOOKUP($D11,基础参数!$A$6:$C$22,2,FALSE),"")) | F11: =IF($C11="","",IFERROR(VLOOKUP($D11,基础参数!$A$6:$C$22,3,FALSE),"")) | K11: =IF($C11="","",IF($I11*$J11=0,"",ROUNDUP($AH11*$G11/($I11*$J11),0))) | L11: =IF($C11="","",IF($AH11=0,"",$K11*$I11*$H11/$AH11)) | M11: =IF($C11="","",$L11*$E11) | Q11: =IF($C11="","",IF($AH11=0,"",($P11+$AH11*$N11*$O11/60)*VLOOKUP("PROFILE_SAW",基础参数!$F$6:$I$30,4,FALSE)/$AH11)) | T11: =IF($C11="","",$R11*$S11/60*VLOOKUP("PROFILE_DRILL",基础参数!$F$6:$I$30,4,FALSE)) | W11: =IF($C11="","",$U11*$V11/60*VLOOKUP("PROFILE_TAP",基础参数!$F$6:$I$30,4,FALSE)) | AA11: =IF($C11="","",$Z11/60*VLOOKUP("PROFILE_ASSEMBLY",基础参数!$F$6:$I$30,4,FALSE)) | AC11: =IF($C11="","",$AB11/60*VLOOKUP("WELD",基础参数!$F$6:$I$30,4,FALSE)) | AF11: =IF($C11="","",$AJ11*基础参数!$N$6) | AG11: =IF($C11="","",$AJ11+$AF11) | AI11: =IF($C11="","",$AG11*$AH11) | AJ11: =IF($C11="","",SUM($M11,$Q11,$T11,$W11:$Y11,$AA11,$AC11:$AE11)*(1+基础参数!$N$7)) | AO11: =IF(OR($C11="",AK11=""),"",AJ11-AK11) | AP11: =IFERROR(AO11/AJ11,"")
A12: =IF($C12="","",ROW()-6) | E12: =IF($C12="","",IFERROR(VLOOKUP($D12,基础参数!$A$6:$C$22,2,FALSE),"")) | F12: =IF($C12="","",IFERROR(VLOOKUP($D12,基础参数!$A$6:$C$22,3,FALSE),"")) | K12: =IF($C12="","",IF($I12*$J12=0,"",ROUNDUP($AH12*$G12/($I12*$J12),0))) | L12: =IF($C12="","",IF($AH12=0,"",$K12*$I12*$H12/$AH12)) | M12: =IF($C12="","",$L12*$E12) | Q12: =IF($C12="","",IF($AH12=0,"",($P12+$AH12*$N12*$O12/60)*VLOOKUP("PROFILE_SAW",基础参数!$F$6:$I$30,4,FALSE)/$AH12)) | T12: =IF($C12="","",$R12*$S12/60*VLOOKUP("PROFILE_DRILL",基础参数!$F$6:$I$30,4,FALSE)) | W12: =IF($C12="","",$U12*$V12/60*VLOOKUP("PROFILE_TAP",基础参数!$F$6:$I$30,4,FALSE)) | AA12: =IF($C12="","",$Z12/60*VLOOKUP("PROFILE_ASSEMBLY",基础参数!$F$6:$I$30,4,FALSE)) | AC12: =IF($C12="","",$AB12/60*VLOOKUP("WELD",基础参数!$F$6:$I$30,4,FALSE)) | AF12: =IF($C12="","",$AJ12*基础参数!$N$6) | AG12: =IF($C12="","",$AJ12+$AF12) | AI12: =IF($C12="","",$AG12*$AH12) | AJ12: =IF($C12="","",SUM($M12,$Q12,$T12,$W12:$Y12,$AA12,$AC12:$AE12)*(1+基础参数!$N$7)) | AO12: =IF(OR($C12="",AK12=""),"",AJ12-AK12) | AP12: =IFERROR(AO12/AJ12,"")

Sheet 基础参数
A1: 公司名称
A2: 四类零件报价基础参数
A3: 材料价和加工件费率来自当前加工件模板；新增三类费率为评审初值。蓝色单元格均可修改，修改后各类别报价自动重算。
A4: 材料参数 | F4: 工序费率 | L4: 通用报价参数
A5: 材料代码 | B5: 材料单价(元/kg) | C5: 密度(kg/mm³) | D5: 来源/说明 | F5: 工序代码 | G5: 类别 | H5: 工序名称 | I5: 费率 | J5: 单位 | L5: 参数代码 | M5: 参数名称 | N5: 数值 | O5: 说明
A6: S50C | B6: 6.5 | C6: 7.85e-06 | D6: 当前加工件模板 | F6: LATHE | G6: 加工件 | H6: 车床 | I6: 50 | J6: 元/h | L6: tax_rate | M6: 税率 | N6: 0.13 | O6: 沿用当前加工件模板；正式报价前由财务确认
A7: A6061T6 | B7: 27 | C7: 2.75e-06 | D7: 当前加工件模板 | F7: MILL | G7: 加工件 | H7: 铣床 | I7: 45 | J7: 元/h | L7: quote_markup | M7: 综合加成率 | N7: 0 | O7: 默认0%，保持与加工件模板一致；可用于管理费/利润
A8: 鋁 | B8: 25 | C8: 2.75e-06 | D8: 当前加工件模板 | F8: GRIND | G8: 加工件 | H8: 磨床 | I8: 45 | J8: 元/h | L8: summary_rows | M8: 汇总预留行数 | N8: 500 | O8: 统一汇总统计第7～506行
A9: 电木A級 | B9: 23 | C9: 1.6e-06 | D9: 当前加工件模板 | F9: FITTER | G9: 加工件 | H9: 钳工 | I9: 35 | J9: 元/h | L9: source_template | M9: 源模板 | N9: lfaF_cost_template.xlsx | O9: 用户指定的加工件计算方式
A10: 電木B級 | B10: 18 | C10: 1.6e-06 | D10: 当前加工件模板 | F10: OTHER | G10: 加工件 | H10: 其它 | I10: 30 | J10: 元/h
A11: 4Cr13 | B11: 23 | C11: 7.9e-06 | D11: 当前加工件模板 | F11: EDM | G11: 加工件 | H11: 放电 | I11: 40 | J11: 元/h
A12: 亚克力 | B12: 28 | C12: 1.2e-06 | D12: 当前加工件模板 | F12: WIRE_FAST | G12: 加工件 | H12: 快丝 | I12: 25 | J12: 元/h
A13: 铍铜 | B13: 280 | C13: 8.3e-06 | D13: 当前加工件模板 | F13: WIRE_SLOW | G13: 加工件 | H13: 慢丝 | I13: 70 | J13: 元/h
A14: 黃銅 | B14: 50 | C14: 8.9e-06 | D14: 当前加工件模板 | F14: ENGRAVE | G14: 加工件 | H14: 精雕机 | I14: 40 | J14: 元/h
A15: H13 | B15: 50 | C15: 7.9e-06 | D15: 当前加工件模板 | F15: CNC | G15: 加工件 | H15: CNC | I15: 60 | J15: 元/h
A16: 鋼S136H | B16: 120 | C16: 7.9e-06 | D16: 当前加工件模板 | F16: CHROME | G16: 加工件 | H16: 镀铬 | I16: 3 | J16: 元/kg
A17: 鋼S136 | B17: 60 | C17: 7.9e-06 | D17: 当前加工件模板 | F17: HEAT | G17: 加工件 | H17: 热处理 | I17: 12 | J17: 元/kg
A18: 鐵 | B18: 6.5 | C18: 7.85e-06 | D18: 当前加工件模板 | F18: ANODIZE | G18: 加工件 | H18: 阳极 | I18: 12 | J18: 元/kg
A19: Q235 | B19: 6.5 | C19: 7.85e-06 | D19: 新增示例，须按采购价校准 | F19: BLACK | G19: 加工件 | H19: 发黑 | I19: 2 | J19: 元/kg
A20: SUS304 | B20: 18 | C20: 7.93e-06 | D20: 新增示例，须按采购价校准 | F20: SM_LASER | G20: 钣金件 | H20: 激光切割 | I20: 220 | J20: 元/h
A21: SUS316 | B21: 28 | C21: 7.98e-06 | D21: 新增示例，须按采购价校准 | F21: SM_BEND | G21: 钣金件 | H21: 折弯 | I21: 140 | J21: 元/h
A22: 镀锌板 | B22: 8 | C22: 7.85e-06 | D22: 新增示例，须按采购价校准 | F22: SM_MANUAL | G22: 钣金件 | H22: 去毛刺/压铆/手工 | I22: 70 | J22: 元/h
F23: WELD_PREP | G23: 焊接件 | H23: 备料/坡口 | I23: 90 | J23: 元/h
F24: WELD_FIT | G24: 焊接件 | H24: 组立/点固 | I24: 90 | J24: 元/h
F25: WELD | G25: 焊接件 | H25: 焊接 | I25: 120 | J25: 元/h
F26: WELD_POST | G26: 焊接件 | H26: 打磨/校形 | I26: 80 | J26: 元/h
F27: PROFILE_SAW | G27: 型材组装件 | H27: 型材锯切 | I27: 110 | J27: 元/h
F28: PROFILE_DRILL | G28: 型材组装件 | H28: 钻孔 | I28: 130 | J28: 元/h
F29: PROFILE_TAP | G29: 型材组装件 | H29: 攻牙 | I29: 120 | J29: 元/h
F30: PROFILE_ASSEMBLY | G30: 型材组装件 | H30: 装配 | I30: 85 | J30: 元/h
